gpxslicer/__init__.py
gpxslicer/__main__.py
gpxslicer/slicer.py
gpxslicer-0.1.0.dist-info/LICENSE
gpxslicer-0.1.0.dist-info/METADATA
gpxslicer-0.1.0.dist-info/WHEEL
gpxslicer-0.1.0.dist-info/entry_points.txt
gpxslicer-0.1.0.dist-info/top_level.txt
gpxslicer-0.1.0.dist-info/RECORD
