Metadata-Version: 2.1
Name: gpxslicer
Version: 0.1.0
Summary: Slice up gpx tracks based on distance from the start or custom waypoints
Home-page: https://github.com/andrashann/gpxslicer
Author: András Hann
Author-email: dev@hann.io
License: Apache License 2.0
Platform: UNKNOWN
Classifier: Development Status :: 4 - Beta
Classifier: Programming Language :: Python :: 3
Classifier: Environment :: Console
Classifier: License :: OSI Approved :: Apache Software License
Classifier: Topic :: Scientific/Engineering :: GIS
Classifier: Topic :: Utilities
Requires-Dist: gpxpy
